pyoctoprintapi/__init__.py
pyoctoprintapi/__main__.py
pyoctoprintapi/api.py
pyoctoprintapi/const.py
pyoctoprintapi/exceptions.py
pyoctoprintapi/job.py
pyoctoprintapi/octoprint_client.py
pyoctoprintapi/printer.py
pyoctoprintapi/server.py
pyoctoprintapi/settings.py
pyoctoprintapi-0.1.14.dist-info/LICENSE
pyoctoprintapi-0.1.14.dist-info/METADATA
pyoctoprintapi-0.1.14.dist-info/WHEEL
pyoctoprintapi-0.1.14.dist-info/top_level.txt
pyoctoprintapi-0.1.14.dist-info/RECORD
